air_labs_bulk_pause_api/__init__.py
air_labs_bulk_pause_api/air_labs_bulk_pause_api.py
air_labs_bulk_pause_api-0.1.1.dist-info/METADATA
air_labs_bulk_pause_api-0.1.1.dist-info/WHEEL
air_labs_bulk_pause_api-0.1.1.dist-info/entry_points.txt
air_labs_bulk_pause_api-0.1.1.dist-info/RECORD
