Metadata-Version: 2.4
Name: air-labs-bulk-pause-api
Version: 0.1.1
Summary: FastAPI plugin to pause/unpause Airflow DAGs in bulk.
Author: Rahul Rajasekharan
License: MIT
Requires-Python: >=3.9
Requires-Dist: air-labs-helpers>=0.1.0
